aspose/psd/py.typed
aspose/pycore/py.typed
aspose/pycore/__init__.pyi
aspose/pyreflection/py.typed
aspose/pyreflection/__init__.pyi
aspose/pydrawing/py.typed
aspose/pydrawing/__init__.pyi
aspose/pydrawing/design.pyi
aspose/pydrawing/drawing2d.pyi
aspose/pydrawing/imaging.pyi
aspose/pydrawing/printing.pyi
aspose/pydrawing/text.pyi
aspose/psd/__init__.pyi
aspose/psd/asynctask/__init__.pyi
aspose/psd/brushes/__init__.pyi
aspose/psd/coreexceptions/__init__.pyi
aspose/psd/coreexceptions/compressors/__init__.pyi
aspose/psd/coreexceptions/imageformats/__init__.pyi
aspose/psd/customfonthandler/__init__.pyi
aspose/psd/dithering/__init__.pyi
aspose/psd/evalute/__init__.pyi
aspose/psd/exif/__init__.pyi
aspose/psd/exif/enums/__init__.pyi
aspose/psd/extensions/__init__.pyi
aspose/psd/fileformats/__init__.pyi
aspose/psd/fileformats/ai/__init__.pyi
aspose/psd/fileformats/bmp/__init__.pyi
aspose/psd/fileformats/core/__init__.pyi
aspose/psd/fileformats/core/blending/__init__.pyi
aspose/psd/fileformats/core/vectorpaths/__init__.pyi
aspose/psd/fileformats/jpeg/__init__.pyi
aspose/psd/fileformats/jpeg2000/__init__.pyi
aspose/psd/fileformats/pdf/__init__.pyi
aspose/psd/fileformats/png/__init__.pyi
aspose/psd/fileformats/psd/__init__.pyi
aspose/psd/fileformats/psd/core/__init__.pyi
aspose/psd/fileformats/psd/core/rawcolor/__init__.pyi
aspose/psd/fileformats/psd/layers/__init__.pyi
aspose/psd/fileformats/psd/layers/adjustmentlayers/__init__.pyi
aspose/psd/fileformats/psd/layers/animation/__init__.pyi
aspose/psd/fileformats/psd/layers/filllayers/__init__.pyi
aspose/psd/fileformats/psd/layers/fillsettings/__init__.pyi
aspose/psd/fileformats/psd/layers/gradient/__init__.pyi
aspose/psd/fileformats/psd/layers/layereffects/__init__.pyi
aspose/psd/fileformats/psd/layers/layerresources/__init__.pyi
aspose/psd/fileformats/psd/layers/layerresources/strokeresources/__init__.pyi
aspose/psd/fileformats/psd/layers/layerresources/typetoolinfostructures/__init__.pyi
aspose_psd-26.1.0.dist-info/METADATA
aspose_psd-26.1.0.dist-info/WHEEL
aspose_psd-26.1.0.dist-info/entry_points.txt
aspose_psd-26.1.0.dist-info/top_level.txt
aspose_psd-26.1.0.dist-info/RECORD