Metadata-Version: 2.1
Name: aspose-psd
Version: 26.1.0
Summary: Aspose.PSD for Python via .NET is a standalone API to read, write, process, convert Adobe Photoshop PSD, PSB formats without needing to install Adobe Photoshop® and AI files without Adobe Illustrator®
Home-page: https://products.aspose.com/psd/python-net
Author: Aspose
License: Free To Use But Restricted,Other/Proprietary License
Project-URL: API Reference, https://reference.aspose.com/psd/python-net/
Project-URL: Blog, https://blog.aspose.com/categories/aspose.psd-product-family/
Project-URL: Demos, https://products.aspose.app/psd/family
Project-URL: Docs, https://docs.aspose.com/psd/python-net/
Project-URL: Examples, https://github.com/aspose-psd/Aspose.PSD-for-Python-NET
Project-URL: Free Support, https://forum.aspose.com/c/psd
Project-URL: Release Notes, https://docs.aspose.com/psd/python-net/release-notes/
Project-URL: Temporary License, https://purchase.aspose.com/temporary-license
Keywords: Aspose.PSD,ICC,Profile,CMYK,RGBA,LAB,Grayscale,Color,Modes,Layers,Images,Drawing,Export,Effects,Filters,Mask,Masking,Graphics,Watermark,Rendering,Text,Editing,Paths,Groups,Adjustment,Smart,Objects,Blending,Manipulation,API,Adobe,Photoshop,Illustrator,PSD,PSB,AI,GIF,JPEG,JPG,JPEG2000,BMP,PDF,PNG,TIF,TIFF
Platform: win_amd64
Classifier: Development Status :: 5 - Production/Stable
Classifier: Intended Audience :: Developers
Classifier: Intended Audience :: Education
Classifier: Intended Audience :: Other Audience
Classifier: Operating System :: Microsoft :: Windows
Classifier: Operating System :: POSIX :: Linux
Classifier: Operating System :: Unix
Classifier: Operating System :: MacOS :: MacOS X
Classifier: Environment :: MacOS X
Classifier: Topic :: Office/Business
Classifier: Topic :: Software Development
Classifier: Topic :: Software Development :: Libraries
Classifier: Topic :: Multimedia :: Graphics
Classifier: Topic :: Multimedia :: Graphics :: Graphics Conversion
Classifier: Topic :: Scientific/Engineering :: Image Processing
Classifier: Programming Language :: Python :: 3
Classifier: Programming Language :: Python :: 3 :: Only
Classifier: Programming Language :: Python :: 3.5
Classifier: Programming Language :: Python :: 3.6
Classifier: Programming Language :: Python :: 3.7
Classifier: Programming Language :: Python :: 3.8
Classifier: Programming Language :: Python :: 3.9
Classifier: Programming Language :: Python :: 3.10
Classifier: Programming Language :: Python :: 3.11
Classifier: Programming Language :: Python :: 3.12
Classifier: Programming Language :: Python :: 3.13
Requires-Python: >=3.5,<3.14
